HISTORY.rst
LICENSE
MANIFEST.in
README.rst
setup.py
nose_seed_faker.egg-info/PKG-INFO
nose_seed_faker.egg-info/SOURCES.txt
nose_seed_faker.egg-info/dependency_links.txt
nose_seed_faker.egg-info/entry_points.txt
nose_seed_faker.egg-info/not-zip-safe
nose_seed_faker.egg-info/requires.txt
nose_seed_faker.egg-info/top_level.txt
seedfaker/__init__.py
seedfaker/_version.py
seedfaker/plugin.py