Metadata-Version: 1.1
Name: nose-seed-faker
Version: 0.1.2
Summary: A Nose plugin that seeds the faker package.
Home-page: https://github.com/venmo/nose-seed-faker
Author: Amy Hanlon
Author-email: amy@venmo.com
License: MIT
Platform: UNKNOWN
Classifier: Development Status :: 4 - Beta
Classifier: Intended Audience :: Developers
Classifier: License :: OSI Approved :: MIT License
Classifier: Programming Language :: Python
Classifier: Programming Language :: Python :: 2.7
